{
  "stock_code": "005930",
  "corp_name": "삼성전자",
  "updated_at": "2026-07-21T12:52:37.113436",
  "financials_yearly": [
    {
      "year": 2022,
      "영업이익": 43376630000000,
      "매출액": 302231360000000
    },
    {
      "year": 2023,
      "영업이익": 6566976000000,
      "매출액": 258935494000000,
      "매출액_YoY(%)": -14.3,
      "영업이익_YoY(%)": -84.9
    },
    {
      "year": 2024,
      "영업이익": 32725961000000,
      "매출액": 300870903000000,
      "매출액_YoY(%)": 16.2,
      "영업이익_YoY(%)": 398.3
    },
    {
      "year": 2025,
      "영업이익": 43601051000000,
      "매출액": 333605938000000,
      "매출액_YoY(%)": 10.9,
      "영업이익_YoY(%)": 33.2
    }
  ],
  "price": {
    "current_price": 259000,
    "prev_diff": 15000,
    "prev_diff_rate": 6.15,
    "market_status": "CLOSE",
    "traded_at": "2026-07-21T20:00:00.000000+09:00",
    "per": 20.93,
    "eps": 12372.0,
    "source": "naver_realtime"
  },
  "consensus": {
    "target_price": 513958,
    "recomm_mean": 4.04,
    "consensus_date": "2026-07-20",
    "forward_eps": 46664.0,
    "forward_per": 5.55,
    "current_per": 20.93,
    "current_eps": 12372.0,
    "week52_high": 380000.0,
    "week52_low": 64900.0,
    "industry_code": "278",
    "current_price": 259000,
    "prev_diff": 15000,
    "prev_diff_text": "상승",
    "trade_date": "20260721"
  },
  "forward_valuation": {
    "forward_eps": 46664.0,
    "forward_per": 5.55,
    "is_estimate": true,
    "note": "증권가 컨센서스 추정 EPS 기준 (네이버 모바일증권 API)"
  },
  "week52": {
    "position_pct": 61.6
  },
  "sector_comparison": {
    "domestic": {
      "peer_count": 5,
      "peers": [
        {
          "code": "000660",
          "name": "SK하이닉스",
          "per": 17.74,
          "forward_per": 5.83
        },
        {
          "code": "402340",
          "name": "SK스퀘어",
          "per": 10.64,
          "forward_per": 4.23
        },
        {
          "code": "042700",
          "name": "한미반도체",
          "per": 119.98,
          "forward_per": null
        },
        {
          "code": "036930",
          "name": "주성엔지니어링",
          "per": 1175.0,
          "forward_per": null
        },
        {
          "code": "007660",
          "name": "이수페타시스",
          "per": 37.35,
          "forward_per": 24.61
        }
      ]
    },
    "us": {
      "peer_count": 0,
      "peers": [],
      "error": "401 Client Error: Unauthorized for url: https://query1.finance.yahoo.com/v7/finance/quote?symbols=MU%2CTSM%2CINTC",
      "note": "Yahoo 비공식 API 호출 실패 - 형식이 바뀌었거나 차단됐을 수 있음"
    }
  },
  "technical": {
    "ma5": 260100.0,
    "ma20": 296250.0,
    "ma60": 293466.7,
    "ma_alignment": "혼조",
    "rsi14": 42.3,
    "macd": {
      "macd": -15936.12,
      "signal": -9684.79,
      "histogram": -6251.33
    },
    "volume_surge_ratio": 0.64
  },
  "supply_demand": {
    "days_used": 5,
    "foreigner_net_sum": 2918011.0,
    "institution_net_sum": 699540.0,
    "individual_net_sum": -3682956.0,
    "foreigner_streak_days": 2
  },
  "scores": {
    "short_term": {
      "score": 40,
      "factors": {
        "ma_alignment": "혼조",
        "rsi14": 42.3,
        "macd_histogram": -6251.33,
        "volume_surge_ratio": 0.64
      },
      "note": "이동평균 배열 + RSI + MACD + 거래량. 확정 매매신호 아님(참고용)."
    },
    "mid_term": {
      "score": 81,
      "factors": {
        "foreigner_streak_days": 2,
        "foreigner_net_sum": 2918011.0,
        "target_upside_pct": 98.4
      },
      "note": "외국인 수급 추이 + 목표주가 괴리율. 확정 매매신호 아님(참고용)."
    },
    "long_term": {
      "score": 74.7,
      "factors": {
        "revenue_yoy_pct": 10.9,
        "target_upside_pct": 98.4,
        "week52_position_pct": 61.6
      },
      "note": "성장률 + 목표주가 괴리율 + 52주위치. 자기 과거 PER밴드 비교는 아직 미반영. 확정 매매신호 아님(참고용)."
    }
  },
  "recent_disclosures": [
    {
      "title": "임원ㆍ주요주주특정증권등소유상황보고서",
      "date": "20260721",
      "rcept_no": "20260721001369"
    },
    {
      "title": "임원ㆍ주요주주특정증권등소유상황보고서",
      "date": "20260721",
      "rcept_no": "20260721001365"
    },
    {
      "title": "임원ㆍ주요주주특정증권등소유상황보고서",
      "date": "20260721",
      "rcept_no": "20260721001362"
    },
    {
      "title": "임원ㆍ주요주주특정증권등소유상황보고서",
      "date": "20260721",
      "rcept_no": "20260721001360"
    },
    {
      "title": "임원ㆍ주요주주특정증권등소유상황보고서",
      "date": "20260721",
      "rcept_no": "20260721001358"
    },
    {
      "title": "임원ㆍ주요주주특정증권등소유상황보고서",
      "date": "20260721",
      "rcept_no": "20260721001353"
    },
    {
      "title": "임원ㆍ주요주주특정증권등소유상황보고서",
      "date": "20260721",
      "rcept_no": "20260721001351"
    },
    {
      "title": "임원ㆍ주요주주특정증권등소유상황보고서",
      "date": "20260721",
      "rcept_no": "20260721001348"
    },
    {
      "title": "임원ㆍ주요주주특정증권등소유상황보고서",
      "date": "20260721",
      "rcept_no": "20260721001346"
    },
    {
      "title": "임원ㆍ주요주주특정증권등소유상황보고서",
      "date": "20260721",
      "rcept_no": "20260721001345"
    },
    {
      "title": "임원ㆍ주요주주특정증권등소유상황보고서",
      "date": "20260721",
      "rcept_no": "20260721001338"
    },
    {
      "title": "임원ㆍ주요주주특정증권등소유상황보고서",
      "date": "20260721",
      "rcept_no": "20260721001337"
    },
    {
      "title": "임원ㆍ주요주주특정증권등소유상황보고서",
      "date": "20260721",
      "rcept_no": "20260721001333"
    },
    {
      "title": "임원ㆍ주요주주특정증권등소유상황보고서",
      "date": "20260721",
      "rcept_no": "20260721001331"
    },
    {
      "title": "임원ㆍ주요주주특정증권등소유상황보고서",
      "date": "20260721",
      "rcept_no": "20260721001330"
    }
  ]
}